<settings xmlns="http://maven.apache.org/SETTINGS/1.0.0"
          xmlns:xsi="http://www.w3.org/2001/XMLSchema-instance"
          xsi:schemaLocation="http://maven.apache.org/SETTINGS/1.0.0 http://maven.apache.org/xsd/settings-1.0.0.xsd">
    <servers>
        <server>
            <id>bintray-justin-wesley-maven</id>
            <username>${env.BINTRAY_USER}</username>
            <password>${env.BINTRAY_API_KEY}</password>
        </server>
        <server>
            <id>github.com</id>
            <username>${env.GITHUB_USER}</username>
            <password>${env.GITHUB_PASSWORD}</password>
        </server>
        <server>
            <id>ossrh</id>
            <username>${env.OSS_USER}</username>
            <password>${env.OSS_PASSWORD}</password>
        </server>
    </servers>
    <localRepository>./repo</localRepository>
    <profiles>
        <profile>
            <id>bintray</id>
            <repositories>
                <repository>
                    <id>central</id>
                    <name>bintray</name>
                    <url>http://jcenter.bintray.com</url>
                    <snapshots>
                        <enabled>false</enabled>
                    </snapshots>
                </repository>
                <repository>
                    <id>ossnexus</id>
                    <name>Sonatype Snapshots Repository</name>
                    <url>https://oss.sonatype.org/content/repositories/snapshots/</url>
                    <snapshots>
                        <enabled>true</enabled>
                    </snapshots>
                    <releases>
                        <enabled>false</enabled>
                    </releases>
                </repository>
                <repository>
                    <id>justin-wesley-bintray</id>
                    <name>Justin Wesley Personal Repository</name>
                    <url>https://dl.bintray.com/justin-wesley/maven/</url>
                    <snapshots>
                        <enabled>false</enabled>
                    </snapshots>
                    <releases>
                        <enabled>true</enabled>
                    </releases>
                </repository>
            </repositories>
            <pluginRepositories>
                <pluginRepository>
                    <snapshots>
                        <enabled>false</enabled>
                    </snapshots>
                    <id>central</id>
                    <name>bintray-plugins</name>
                    <url>http://jcenter.bintray.com</url>
                </pluginRepository>
            </pluginRepositories>
        </profile>
    </profiles>
    <activeProfiles>
        <activeProfile>bintray</activeProfile>
    </activeProfiles>
</settings>